ceilometer/__init__.py
ceilometer/agent.py
ceilometer/cache_utils.py
ceilometer/declarative.py
ceilometer/gnocchi_client.py
ceilometer/i18n.py
ceilometer/keystone_client.py
ceilometer/messaging.py
ceilometer/middleware.py
ceilometer/neutron_client.py
ceilometer/notification.py
ceilometer/nova_client.py
ceilometer/opts.py
ceilometer/sample.py
ceilometer/service.py
ceilometer/utils.py
ceilometer/version.py
ceilometer/alarm/__init__.py
ceilometer/alarm/aodh.py
ceilometer/alarm/discovery.py
ceilometer/cmd/__init__.py
ceilometer/cmd/agent_notification.py
ceilometer/cmd/polling.py
ceilometer/cmd/sample.py
ceilometer/cmd/status.py
ceilometer/cmd/storage.py
ceilometer/compute/__init__.py
ceilometer/compute/discovery.py
ceilometer/compute/pollsters/__init__.py
ceilometer/compute/pollsters/disk.py
ceilometer/compute/pollsters/instance_stats.py
ceilometer/compute/pollsters/net.py
ceilometer/compute/pollsters/util.py
ceilometer/compute/virt/__init__.py
ceilometer/compute/virt/inspector.py
ceilometer/compute/virt/libvirt/__init__.py
ceilometer/compute/virt/libvirt/inspector.py
ceilometer/compute/virt/libvirt/utils.py
ceilometer/data/meters.d/meters.yaml
ceilometer/event/__init__.py
ceilometer/event/converter.py
ceilometer/event/models.py
ceilometer/event/trait_plugins.py
ceilometer/hacking/__init__.py
ceilometer/hacking/checks.py
ceilometer/image/__init__.py
ceilometer/image/discovery.py
ceilometer/image/glance.py
ceilometer/ipmi/__init__.py
ceilometer/ipmi/notifications/__init__.py
ceilometer/ipmi/notifications/ironic.py
ceilometer/ipmi/platform/__init__.py
ceilometer/ipmi/platform/exception.py
ceilometer/ipmi/platform/ipmi_sensor.py
ceilometer/ipmi/platform/ipmitool.py
ceilometer/ipmi/pollsters/__init__.py
ceilometer/ipmi/pollsters/sensor.py
ceilometer/locale/de/LC_MESSAGES/ceilometer.po
ceilometer/locale/en_GB/LC_MESSAGES/ceilometer.po
ceilometer/locale/es/LC_MESSAGES/ceilometer.po
ceilometer/locale/fr/LC_MESSAGES/ceilometer.po
ceilometer/locale/it/LC_MESSAGES/ceilometer.po
ceilometer-25.0.0.dist-info/AUTHORS
ceilometer-25.0.0.dist-info/LICENSE
ceilometer-25.0.0.dist-info/METADATA
ceilometer-25.0.0.dist-info/WHEEL
ceilometer-25.0.0.dist-info/entry_points.txt
ceilometer-25.0.0.dist-info/pbr.json
ceilometer-25.0.0.dist-info/top_level.txt
ceilometer-25.0.0.dist-info/RECORD
